CHANGELOG
MANIFEST.in
README
setup.py
cms_social_facebook/__init__.py
cms_social_facebook/cms_plugins.py
cms_social_facebook/models.py
cms_social_facebook/templates/cms_social_facebook/.livestream.html.swp
cms_social_facebook/templates/cms_social_facebook/comments.html
cms_social_facebook/templates/cms_social_facebook/facepile.html
cms_social_facebook/templates/cms_social_facebook/like.html
cms_social_facebook/templates/cms_social_facebook/likebox.html
cms_social_facebook/templates/cms_social_facebook/livestream.html
cms_social_facebook/templates/cms_social_facebook/loginbutton.html
django_cms_social_networks.egg-info/PKG-INFO
django_cms_social_networks.egg-info/SOURCES.txt
django_cms_social_networks.egg-info/dependency_links.txt
django_cms_social_networks.egg-info/not-zip-safe
django_cms_social_networks.egg-info/requires.txt
django_cms_social_networks.egg-info/top_level.txt