Metadata-Version: 1.0
Name: django-cms-social-networks
Version: 0.1.0
Summary: Django CMS Social Networks Plugins
Home-page: http://github.com/psaavedra/django-cms-social-networks
Author: Pablo Saavedra
Author-email: pablo.saavedra@treitos.com
License: Copyright (R) - 2011 Treitos
